elsysco/__init__.py
elsysco/hyperweb/__init__.py
elsysco-1.0.2.dist-info/LICENSE.txt
elsysco-1.0.2.dist-info/METADATA
elsysco-1.0.2.dist-info/WHEEL
elsysco-1.0.2.dist-info/top_level.txt
elsysco-1.0.2.dist-info/RECORD
