Metadata-Version: 2.1
Name: elsysco
Version: 1.0.2
Summary: ELEGANT SYSTEM COMPONENT
Home-page: https://github.com/pythonsystem/elsysco
Author: Digital Community
License: MIT
License-File: LICENSE.txt
Requires-Dist: httpx ==0.27.0
